.gitignore
AUTHORS
LICENSE
README.rst
setup.py
django_purls.egg-info/PKG-INFO
django_purls.egg-info/SOURCES.txt
django_purls.egg-info/dependency_links.txt
django_purls.egg-info/not-zip-safe
django_purls.egg-info/top_level.txt
purls/__init__.py
purls/serverring.py
purls/tests.py
purls/templatetags/__init__.py
purls/templatetags/purl_tags.py