Metadata-Version: 1.0
Name: django-purls
Version: 0.3
Summary: django-purls
Home-page: http://github.com/macro/django-purls/
Author: Neil Chintomby
Author-email: nchintomby+django@gmail.com
License: BSD
Keywords: performance,static,content,parallel,urls,django
Platform: UNKNOWN
Classifier: Programming Language :: Python
Classifier: Topic :: Software Development :: Libraries :: Python Modules
Classifier: Framework :: Django
Classifier: Environment :: Web Environment
